[
  {
    "title": "Trump finally sealed his Iran deal. Now talks on the ‘final’ deal begin. - NBC News",
    "summary": "Trump finally sealed his Iran deal. Now talks on the ‘final’ deal begin. - NBC News",
    "source": "unknown",
    "time": ""
  },
  {
    "title": "Vance warns Israeli critics over Iran deal: Trump is your only ally - Reuters",
    "summary": "Vance warns Israeli critics over Iran deal: Trump is your only ally - Reuters",
    "source": "unknown",
    "time": ""
  },
  {
    "title": "Trump administration compares reflecting pool algae battle to Iran war - The Guardian",
    "summary": "Trump administration compares reflecting pool algae battle to Iran war - The Guardian",
    "source": "unknown",
    "time": ""
  },
  {
    "title": "Mangione Withdraws Emotional Disturbance Defense in New York Case - The New York Times",
    "summary": "Mangione Withdraws Emotional Disturbance Defense in New York Case - The New York Times",
    "source": "unknown",
    "time": ""
  },
  {
    "title": "Ukraine hits a Moscow oil refinery and other sites in a large-scale drone attack - NPR",
    "summary": "Ukraine hits a Moscow oil refinery and other sites in a large-scale drone attack - NPR",
    "source": "unknown",
    "time": ""
  },
  {
    "title": "Opening his presidential center, Obama urges resistance to ‘cynicism and despair’ - CNN",
    "summary": "Opening his presidential center, Obama urges resistance to ‘cynicism and despair’ - CNN",
    "source": "unknown",
    "time": ""
  },
  {
    "title": "Janeese Lewis George wins the Democratic primary for mayor of Washington, DC - AP News",
    "summary": "Janeese Lewis George wins the Democratic primary for mayor of Washington, DC - AP News",
    "source": "unknown",
    "time": ""
  },
  {
    "title": "Bowen: US-Iran deal raises inescapable question of what the war was for - BBC",
    "summary": "Bowen: US-Iran deal raises inescapable question of what the war was for - BBC",
    "source": "unknown",
    "time": ""
  },
  {
    "title": "Fed governor Lisa Cook faced $1.3m in legal and security fees after Trump’s bid to fire her - The Guardian",
    "summary": "Fed governor Lisa Cook faced $1.3m in legal and security fees after Trump’s bid to fire her - The Guardian",
    "source": "unknown",
    "time": ""
  },
  {
    "title": "Colorado Governor Overruled His Own Clemency Board to Release Tina Peters - The New York Times",
    "summary": "Colorado Governor Overruled His Own Clemency Board to Release Tina Peters - The New York Times",
    "source": "unknown",
    "time": ""
  },
  {
    "title": "Man charged with attempted murder after toddler ends up in crocodile enclosure at U.K. zoo - CBS News",
    "summary": "Man charged with attempted murder after toddler ends up in crocodile enclosure at U.K. zoo - CBS News",
    "source": "unknown",
    "time": ""
  },
  {
    "title": "Macron’s diplomatic efforts bring Trump closer to European views - AP News",
    "summary": "Macron’s diplomatic efforts bring Trump closer to European views - AP News",
    "source": "unknown",
    "time": ""
  },
  {
    "title": "Meet the Elite Ukrainian Drone Units, ‘Ace’ Pilots Targeting Russian Fuel Trucks, Logistics - Kyiv Post",
    "summary": "Meet the Elite Ukrainian Drone Units, ‘Ace’ Pilots Targeting Russian Fuel Trucks, Logistics - Kyiv Post",
    "source": "unknown",
    "time": ""
  },
  {
    "title": "EU leaders weigh tougher measures to combat China trade imbalance - Reuters",
    "summary": "EU leaders weigh tougher measures to combat China trade imbalance - Reuters",
    "source": "unknown",
    "time": ""
  },
  {
    "title": "Markets are set for a much more hawkish Warsh Fed than expected - CNBC",
    "summary": "Markets are set for a much more hawkish Warsh Fed than expected - CNBC",
    "source": "unknown",
    "time": ""
  },
  {
    "title": "Gas prices fall below $4 on average after Trump’s signing of Iran deal to end war - The Guardian",
    "summary": "Gas prices fall below $4 on average after Trump’s signing of Iran deal to end war - The Guardian",
    "source": "unknown",
    "time": ""
  },
  {
    "title": "SpaceX shares fall as post-IPO frenzy loses steam - Reuters",
    "summary": "SpaceX shares fall as post-IPO frenzy loses steam - Reuters",
    "source": "unknown",
    "time": ""
  },
  {
    "title": "Accenture Shares Sink 20% After Revenue Outlook Misses Expectations - Yahoo Finance",
    "summary": "Accenture Shares Sink 20% After Revenue Outlook Misses Expectations - Yahoo Finance",
    "source": "unknown",
    "time": ""
  },
  {
    "title": "Photoshop and Premiere now have AI assistants - The Verge",
    "summary": "Photoshop and Premiere now have AI assistants - The Verge",
    "source": "unknown",
    "time": ""
  },
  {
    "title": "You can now use the Game Boy Camera with your phone - The Verge",
    "summary": "You can now use the Game Boy Camera with your phone - The Verge",
    "source": "unknown",
    "time": ""
  },
  {
    "title": "Google will fix Android 17 bug that deletes homescreen widgets for some Pixel owners [U] - 9to5Google",
    "summary": "Google will fix Android 17 bug that deletes homescreen widgets for some Pixel owners [U] - 9to5Google",
    "source": "unknown",
    "time": ""
  },
  {
    "title": "Snap's $2,195 AR glasses may have cost an insane amount to develop, analyst estimates - Yahoo Finance",
    "summary": "Snap's $2,195 AR glasses may have cost an insane amount to develop, analyst estimates - Yahoo Finance",
    "source": "unknown",
    "time": ""
  },
  {
    "title": "Why Netflix Canceled ‘The Boroughs’ (Exclusive) - hollywoodreporter.com",
    "summary": "Why Netflix Canceled ‘The Boroughs’ (Exclusive) - hollywoodreporter.com",
    "source": "unknown",
    "time": ""
  },
  {
    "title": "Former child actor Daveigh Chase, voice of Lilo from 'Lilo and Stitch' and \"The Ring' villain, dies at 35 - ABC7 Los Angeles",
    "summary": "Former child actor Daveigh Chase, voice of Lilo from 'Lilo and Stitch' and \"The Ring' villain, dies at 35 - ABC7 Los Ang",
    "source": "unknown",
    "time": ""
  },
  {
    "title": "Taylor Swift Wrote and Recorded 'I Knew It, I Knew You' in 8 Hours - Variety",
    "summary": "Taylor Swift Wrote and Recorded 'I Knew It, I Knew You' in 8 Hours - Variety",
    "source": "unknown",
    "time": ""
  },
  {
    "title": "Grammy-nominated producer Tay Keith found dead in Nashville apartment, police confirm - WSMV",
    "summary": "Grammy-nominated producer Tay Keith found dead in Nashville apartment, police confirm - WSMV",
    "source": "unknown",
    "time": ""
  },
  {
    "title": "Canada's Ismael Kone suffers horrifying injury in World Cup vs. Qatar - USA Today",
    "summary": "Canada's Ismael Kone suffers horrifying injury in World Cup vs. Qatar - USA Today",
    "source": "unknown",
    "time": ""
  },
  {
    "title": "USMNT's Christian Pulisic trains apart from team again; Pochettino due to address status - ESPN",
    "summary": "USMNT's Christian Pulisic trains apart from team again; Pochettino due to address status - ESPN",
    "source": "unknown",
    "time": ""
  },
  {
    "title": "U.S. Open Round 1 leaderboard: Rory McIlroy in contention on windy day at Shinnecock - Yahoo Sports",
    "summary": "U.S. Open Round 1 leaderboard: Rory McIlroy in contention on windy day at Shinnecock - Yahoo Sports",
    "source": "unknown",
    "time": ""
  },
  {
    "title": "‘UFC Freedom 250’ Averages 8.2 Million Viewers Across U.S. and Latin America - Variety",
    "summary": "‘UFC Freedom 250’ Averages 8.2 Million Viewers Across U.S. and Latin America - Variety",
    "source": "unknown",
    "time": ""
  },
  {
    "title": "NASA Flyby Reveals Violent Origin of Weird Peanut-Shaped Asteroid - Gizmodo",
    "summary": "NASA Flyby Reveals Violent Origin of Weird Peanut-Shaped Asteroid - Gizmodo",
    "source": "unknown",
    "time": ""
  },
  {
    "title": "Ariane 6 launches with more powerful boosters: a new record for Europe - European Space Agency",
    "summary": "Ariane 6 launches with more powerful boosters: a new record for Europe - European Space Agency",
    "source": "unknown",
    "time": ""
  },
  {
    "title": "Stunning Video of the Southern Lights Dancing Across the Earth Captured by a NASA Astronaut–WATCH - Good News Network",
    "summary": "Stunning Video of the Southern Lights Dancing Across the Earth Captured by a NASA Astronaut–WATCH - Good News Network",
    "source": "unknown",
    "time": ""
  },
  {
    "title": "Tension Flared on Space Station as Russia Threatened to Drill and Saw Into Wall, Prompting NASA Astronauts to Take Shelter - Yahoo",
    "summary": "Tension Flared on Space Station as Russia Threatened to Drill and Saw Into Wall, Prompting NASA Astronauts to Take Shelt",
    "source": "unknown",
    "time": ""
  },
  {
    "title": "Hunter-gatherers in Siberia died of a plague outbreak 5,500 years ago - Ars Technica",
    "summary": "Hunter-gatherers in Siberia died of a plague outbreak 5,500 years ago - Ars Technica",
    "source": "unknown",
    "time": ""
  },
  {
    "title": "The Number-1 Sign of Colon Cancer Doctors Say You Shouldn’t Ignore - AOL.com",
    "summary": "The Number-1 Sign of Colon Cancer Doctors Say You Shouldn’t Ignore - AOL.com",
    "source": "unknown",
    "time": ""
  },
  {
    "title": "'I buried my parents one day after the other' - Ebola mourners learn how to grieve safely - BBC",
    "summary": "'I buried my parents one day after the other' - Ebola mourners learn how to grieve safely - BBC",
    "source": "unknown",
    "time": ""
  },
  {
    "title": "New Plan Scales Back C.D.C.’s Work on Diseases Abroad - The New York Times",
    "summary": "New Plan Scales Back C.D.C.’s Work on Diseases Abroad - The New York Times",
    "source": "unknown",
    "time": ""
  }
]